cloudcraftco/__init__.py
cloudcraftco/api_account.py
cloudcraftco/api_blueprint.py
cloudcraftco/api_budget.py
cloudcraftco/api_user.py
cloudcraftco/cloudcraft.py
cloudcraftco/error.py
cloudcraftco-1.1.0.dist-info/LICENSE.md
cloudcraftco-1.1.0.dist-info/METADATA
cloudcraftco-1.1.0.dist-info/WHEEL
cloudcraftco-1.1.0.dist-info/RECORD
