Metadata-Version: 2.1
Name: cloudcraftco
Version: 1.1.0
Summary: Python SDK for rendering AWS and Azure diagrams using the Cloudcraft API.
Home-page: https://www.cloudcraft.co/
License: Apache-2.0
Keywords: datadog,cloudcraft,aws,azure,diagrams,sdk
Author: Datadog, Inc.
Author-email: dev@datadoghq.com
Maintainer: Sean Broderick
Maintainer-email: sean.broderick@datadoghq.com
Requires-Python: >=3.10,<4.0
Classifier: License :: OSI Approved :: Apache Software License
Classifier: Operating System :: OS Independent
Classifier: Programming Language :: Python
Classifier: Programming Language :: Python :: 3
Classifier: Programming Language :: Python :: 3.10
Classifier: Programming Language :: Python :: 3.11
Classifier: Programming Language :: Python :: 3.12
Requires-Dist: requests (>=2.28.1,<3.0.0)
Project-URL: Repository, https://github.com/DataDog/cloudcraft-python
